<?xml version="1.0" encoding="UTF-8" standalone="no"?>
<RightsDefinition AllRights="true">
	<FormRightsCollection>


	</FormRightsCollection>
	<DictRightsCollection>
		<DictDefinition ItemKey="USER_Operator"/>
		<DictDefinition ItemKey="Account"/>
		<DictDefinition ItemKey="AccountChart"/>
		<DictDefinition ItemKey="BusinessArea"/>
		<DictDefinition ItemKey="Calendar"/>
		<DictDefinition ItemKey="Client"/>
		<DictDefinition ItemKey="CompanyCode"/>
		<DictDefinition ItemKey="ControllingArea"/>
		<DictDefinition ItemKey="CostCenter"/>
		<DictDefinition ItemKey="CostCenterGroup"/>
		<DictDefinition ItemKey="Country"/>
		<DictDefinition ItemKey="CreditControlArea"/>
		<DictDefinition ItemKey="Currency"/>
		<DictDefinition ItemKey="Customer"/>
		<DictDefinition ItemKey="CustomerAccountGroup"/>
		<DictDefinition ItemKey="DicModel"/>
		<DictDefinition ItemKey="DistributionChannel"/>
		<DictDefinition ItemKey="Division"/>
		<DictDefinition ItemKey="ExchangeRateType"/>
		<DictDefinition ItemKey="FunctionalArea"/>
		<DictDefinition ItemKey="IndustrySector"/>
		<DictDefinition ItemKey="Language"/>
		<DictDefinition ItemKey="Material"/>
		<DictDefinition ItemKey="MaterialGroup"/>
		<DictDefinition ItemKey="MaterialType"/>
		<DictDefinition ItemKey="PeriodType"/>
		<DictDefinition ItemKey="Plant"/>
		<DictDefinition ItemKey="ProfitCenter"/>
		<DictDefinition ItemKey="PurchasingGroup"/>
		<DictDefinition ItemKey="PurchasingOrganization"/>
		<DictDefinition ItemKey="Region"/>
		<DictDefinition ItemKey="SaleOrganization"/>
		<DictDefinition ItemKey="StorageLocation"/>
		<DictDefinition ItemKey="Unit"/>
		<DictDefinition ItemKey="UnitSystem"/>
		<DictDefinition ItemKey="Vendor"/>
		<DictDefinition ItemKey="VendorAccountGroup"/>
		<DictDefinition ItemKey="VoucherType"/>
		<DictDefinition ItemKey="WorkCenter"/>
		<DictDefinition ItemKey="LRP_Bank"/>
		<DictDefinition ItemKey="LRP_BankAccount"/>
		<DictDefinition ItemKey="LRP_City"/>
		<DictDefinition ItemKey="LRP_DictUserDefault"/>
		<DictDefinition ItemKey="LRP_District"/>
		<DictDefinition ItemKey="LRP_FinicialPeriod"/>
		<DictDefinition ItemKey="LRP_HandlingUnit"/>
		<DictDefinition ItemKey="LRP_HandlingUnitType"/>
		<DictDefinition ItemKey="LRP_Location"/>
		<DictDefinition ItemKey="LRP_LocType"/>
		<DictDefinition ItemKey="LRP_LogisticsService"/>
		<DictDefinition ItemKey="LRP_Lookup"/>
		<DictDefinition ItemKey="LRP_Lookup_L"/>
		<DictDefinition ItemKey="LRP_Material"/>
		<DictDefinition ItemKey="LRP_MaterialStatus"/>
		<DictDefinition ItemKey="LRP_PackingMaterial"/>
		<DictDefinition ItemKey="LRP_PackingMaterialCategory"/>
		<DictDefinition ItemKey="LRP_PackingStrategy"/>
		<DictDefinition ItemKey="LRP_PackingType"/>
		<DictDefinition ItemKey="LRP_PayMethod"/>
		<DictDefinition ItemKey="LRP_Platform"/>
		<DictDefinition ItemKey="LRP_Project"/>
		<DictDefinition ItemKey="LRP_Province"/>
		<DictDefinition ItemKey="LRP_RecvSendParty"/>
		<DictDefinition ItemKey="LRP_Route"/>
		<DictDefinition ItemKey="LRP_Storearea"/>
		<DictDefinition ItemKey="LRP_Storeroom"/>
		<DictDefinition ItemKey="LRP_Trailer"/>
		<DictDefinition ItemKey="LRP_Truck"/>
		<DictDefinition ItemKey="LRP_TruckType"/>
		<DictDefinition ItemKey="LRP_WarehouseTxType"/>
		<DictDefinition ItemKey="LRP_Polygon"/>
		<DictDefinition ItemKey="LRP_Expense"/>
		<DictDefinition ItemKey="LRP_ExpenseType"/>
		<DictDefinition ItemKey="LRP_Income"/>
		<DictDefinition ItemKey="LRP_IncomeType"/>
		<DictDefinition ItemKey="LRP_CouponType"/>
		<DictDefinition ItemKey="LRP_OwnerUser"/>
		<DictDefinition ItemKey="LRP_Driver"/>
		<DictDefinition ItemKey="LRP_Salesperson"/>
		<DictDefinition ItemKey="LRP_WarehouseKeeper"/>
		<DictDefinition ItemKey="LRP_CheckItem"/>
		<DictDefinition ItemKey="LRP_InsuranceCompany"/>
		<DictDefinition ItemKey="LRP_InsuranceType"/>
		<DictDefinition ItemKey="LRP_RepairItem"/>
		<DictDefinition ItemKey="Operator"/>
		<DictDefinition ItemKey="Role"/>
	</DictRightsCollection>
</RightsDefinition>
