<?xml version="1.0" encoding="UTF-8" standalone="no"?>
<DataMigration Caption="调整增加完成日结迁移" Key="DG_402_LRP" SrcDataObjectKey="LRP_WMTx" TgtDataObjectKey="LRP_DailyQuant" StatusFieldKey="Status" StatusValue="finished" HeadCondition="LRP_WMTx_H.TxTypeCode=='402'" Condition="LRP_WMTx_L.Status&gt;=90">
    <SourceTableCollection Height="1050" Width="260" X="30" Y="30">
        <SourceTable TableKey="LRP_WMTx_H">
            <SourceField Definition="WarehouseCenterId" OpSign="Assign" TargetFieldKey="WarehouseCenterId" TargetTableKey="LRP_DailyQuant"/>
            <SourceField Definition="OwnerId" OpSign="Assign" TargetFieldKey="OwnerId" TargetTableKey="LRP_DailyQuant"/>
            <SourceField Definition="TxDateTime" OpSign="Assign" TargetFieldKey="QuantDate" TargetTableKey="LRP_DailyQuant"/>
        </SourceTable>
        <SourceTable TableKey="LRP_WMTx_L" IsPrimary="True">
            <SourceField Definition="MaterialId" OpSign="Assign" TargetFieldKey="MaterialId" TargetTableKey="LRP_DailyQuant"/>
            <SourceField Definition="BasicQty" TargetFieldKey="AdjustAddQty" TargetTableKey="LRP_DailyQuant"/>
			<SourceField Definition="BasicQty" TargetFieldKey="Qty" TargetTableKey="LRP_DailyQuant"/>
            <SourceField Definition="DestBatchNo" OpSign="Assign" TargetFieldKey="BatchNo" TargetTableKey="LRP_DailyQuant"/>
            <SourceField Definition="DestManufDate" OpSign="Assign" TargetFieldKey="ManufDate" TargetTableKey="LRP_DailyQuant"/>
            <SourceField Definition="DestExpireDate" OpSign="Assign" TargetFieldKey="ExpireDate" TargetTableKey="LRP_DailyQuant"/>
            <SourceField Definition="DestProjectId" OpSign="Assign" TargetFieldKey="ProjectId" TargetTableKey="LRP_DailyQuant"/>
            <SourceField Definition="DestRecvDate" OpSign="Assign" TargetFieldKey="RecvDate" TargetTableKey="LRP_DailyQuant"/>
            <SourceField Definition="DestStrUserDef1" OpSign="Assign" TargetFieldKey="StrUserDef1" TargetTableKey="LRP_DailyQuant"/>
            <SourceField Definition="DestStrUserDef2" OpSign="Assign" TargetFieldKey="StrUserDef2" TargetTableKey="LRP_DailyQuant"/>
            <SourceField Definition="DestStrUserDef3" OpSign="Assign" TargetFieldKey="StrUserDef3" TargetTableKey="LRP_DailyQuant"/>
            <SourceField Definition="DestStrUserDef4" OpSign="Assign" TargetFieldKey="StrUserDef4" TargetTableKey="LRP_DailyQuant"/>
            <SourceField Definition="DestStrUserDef5" OpSign="Assign" TargetFieldKey="StrUserDef5" TargetTableKey="LRP_DailyQuant"/>
            <SourceField Definition="DestDictUserDef1" OpSign="Assign" TargetFieldKey="DictUserDef1" TargetTableKey="LRP_DailyQuant"/>
            <SourceField Definition="DestDictUserDef2" OpSign="Assign" TargetFieldKey="DictUserDef2" TargetTableKey="LRP_DailyQuant"/>
            <SourceField Definition="DestDictUserDef3" OpSign="Assign" TargetFieldKey="DictUserDef3" TargetTableKey="LRP_DailyQuant"/>
            <SourceField Definition="DestDictUserDef4" OpSign="Assign" TargetFieldKey="DictUserDef4" TargetTableKey="LRP_DailyQuant"/>
            <SourceField Definition="DestDictUserDef5" OpSign="Assign" TargetFieldKey="DictUserDef5" TargetTableKey="LRP_DailyQuant"/>
            <SourceField Definition="DestDateUserDef1" OpSign="Assign" TargetFieldKey="DateUserDef1" TargetTableKey="LRP_DailyQuant"/>
            <SourceField Definition="DestDateUserDef2" OpSign="Assign" TargetFieldKey="DateUserDef2" TargetTableKey="LRP_DailyQuant"/>
            <SourceField Definition="DestNumUserDef1" TargetFieldKey="NumUserDef1" TargetTableKey="LRP_DailyQuant"/>
            <SourceField Definition="DestNumUserDef2" TargetFieldKey="NumUserDef2" TargetTableKey="LRP_DailyQuant"/>
            <SourceField Definition="DestNumUserDef3" TargetFieldKey="NumUserDef3" TargetTableKey="LRP_DailyQuant"/>
            <SourceField Definition="DestStoreroomId" OpSign="Assign" TargetFieldKey="StoreroomId" TargetTableKey="LRP_DailyQuant"/>
            <SourceField Definition="DestStoreareaId" OpSign="Assign" TargetFieldKey="StoreareaId" TargetTableKey="LRP_DailyQuant"/>
            <SourceField Definition="DestLocationId" OpSign="Assign" TargetFieldKey="LocationId" TargetTableKey="LRP_DailyQuant"/>
            <SourceField Definition="DestMaterialStatusId" OpSign="Assign" TargetFieldKey="MaterialStatusId" TargetTableKey="LRP_DailyQuant"/>
        </SourceTable>
    </SourceTableCollection>
    <TargetTableCollection Height="990" Width="227" X="449" Y="22">
        <TargetTable TableKey="LRP_DailyQuant">
            <TargetField FieldKey="WarehouseCenterId"/>
            <TargetField FieldKey="OwnerId"/>
            <TargetField FieldKey="QuantDate"/>
            <TargetField FieldKey="MaterialId"/>
            <TargetField FieldKey="AdjustAddQty"/>
			<TargetField FieldKey="Qty"/>
            <TargetField FieldKey="BatchNo"/>
            <TargetField FieldKey="ManufDate"/>
            <TargetField FieldKey="ExpireDate"/>
            <TargetField FieldKey="ProjectId"/>
            <TargetField FieldKey="RecvDate"/>
            <TargetField FieldKey="StrUserDef1"/>
            <TargetField FieldKey="StrUserDef2"/>
            <TargetField FieldKey="StrUserDef3"/>
            <TargetField FieldKey="StrUserDef4"/>
            <TargetField FieldKey="StrUserDef5"/>
            <TargetField FieldKey="DictUserDef1"/>
            <TargetField FieldKey="DictUserDef2"/>
            <TargetField FieldKey="DictUserDef3"/>
            <TargetField FieldKey="DictUserDef4"/>
            <TargetField FieldKey="DictUserDef5"/>
            <TargetField FieldKey="DateUserDef1"/>
            <TargetField FieldKey="DateUserDef2"/>
            <TargetField FieldKey="NumUserDef1"/>
            <TargetField FieldKey="NumUserDef2"/>
            <TargetField FieldKey="NumUserDef3"/>
            <TargetField FieldKey="StoreroomId"/>
            <TargetField FieldKey="StoreareaId"/>
            <TargetField FieldKey="LocationId"/>
            <TargetField FieldKey="MaterialStatusId"/>
        </TargetTable>
    </TargetTableCollection>
</DataMigration>
